CHANGELOG.md
csv_permissions/__init__.py
csv_permissions/apps.py
csv_permissions/permissions.py
csv_permissions-0.1.0.dist-info/LICENSE
csv_permissions-0.1.0.dist-info/WHEEL
csv_permissions-0.1.0.dist-info/METADATA
csv_permissions-0.1.0.dist-info/RECORD
