Metadata-Version: 2.1
Name: csv-permissions
Version: 0.1.0
Summary: CSV Based Permissions Module for Django
License: BSD-2-Clause
Keywords: django,permission,alliance,alliancesoftware
Author: Alliance Software
Author-email: support@alliancesoftware.com.au
Requires-Python: >=3.6,<4.0
Classifier: License :: OSI Approved :: BSD License
Classifier: Programming Language :: Python :: 3
Classifier: Programming Language :: Python :: 3.6
Classifier: Programming Language :: Python :: 3.7
Classifier: Programming Language :: Python :: 3.8
Classifier: Programming Language :: Python :: 3.9
Requires-Dist: Django (>=2.2)
Requires-Dist: isort (>=4)
